README.md
setup.py
bfsearch/GridSearch.py
bfsearch/__init__.py
bfsearch.egg-info/PKG-INFO
bfsearch.egg-info/SOURCES.txt
bfsearch.egg-info/dependency_links.txt
bfsearch.egg-info/top_level.txt