Metadata-Version: 1.0
Name: bfsearch
Version: 1.0.3
Summary: A Brute-Force based GridSearch Tool
Home-page: https://github.com/weishengkui/bfsearch
Author: weisk
Author-email: www.7zai@163.com
License: UNKNOWN
Platform: UNKNOWN
